README.md
pyproject.toml
setup.py
mobio/sdks/__init__.py
mobio/sdks/company/__init__.py
mobio/sdks/company/function.py
mobio/sdks/company/helpers/__init__.py
mobio/sdks/company/helpers/redis_helper.py
mobio/sdks/company/helpers/score_similarity.py
mobio/sdks/company/helpers/utils.py
mobio/sdks/company/helpers/unification_helper/__init__.py
mobio/sdks/company/helpers/unification_helper/unified_company_by_source_helper.py
mobio/sdks/company/models/__init__.py
mobio/sdks/company/models/base_model.py
mobio/sdks/company/models/company.py
mobio/sdks/company/models/company_by_satellite.py
mobio/sdks/company/models/db_manager.py
mobio/sdks/company/models/merchant_config.py
mobio_company_sdk.egg-info/PKG-INFO
mobio_company_sdk.egg-info/SOURCES.txt
mobio_company_sdk.egg-info/dependency_links.txt
mobio_company_sdk.egg-info/namespace_packages.txt
mobio_company_sdk.egg-info/requires.txt
mobio_company_sdk.egg-info/top_level.txt